cost2fitness/NNtools.py
cost2fitness/__init__.py
cost2fitness/bar_plots.py
cost2fitness/pipeline.py
cost2fitness/transformers.py
cost2fitness-2.0.7.dist-info/LICENSE
cost2fitness-2.0.7.dist-info/METADATA
cost2fitness-2.0.7.dist-info/WHEEL
cost2fitness-2.0.7.dist-info/top_level.txt
cost2fitness-2.0.7.dist-info/RECORD
