Metadata-Version: 2.1
Name: cost2fitness
Version: 2.0.7
Summary: PyPI package for 1) conversion cost values (less is better) to fitness values (more is better) and vice versa, 2) using fast neural networks for forward propagation
Home-page: https://github.com/PasaOpasen/cost2fitness
Author: Demetry Pascal
Author-email: qtckpuhdsa@gmail.com
Maintainer: ['Demetry Pascal']
License: UNKNOWN
Keywords: optimization,evolutionary algorithms,fast,easy,evolution,generator,simple,converter,min2max,max2min,barplots,reinforcement learning,neural networks,layers
Platform: UNKNOWN
Classifier: Programming Language :: Python :: 3
Classifier: License :: OSI Approved :: MIT License
Classifier: Operating System :: OS Independent
Classifier: Topic :: Software Development :: Libraries :: Python Modules
Requires-Dist: numpy
Requires-Dist: matplotlib
